{
	"en": {
		"newgame": "New Game",
		"language": "Language",
		"back": "back",
		"start": "start game",
		"options": "options",
		"credits": "credits",
		"load": "load",
		"delete_data": "delete stored data",
		"save_data": "save",
		"exit": "exit",
		"pause": "pause",
		"angle": "Angle: $[0]",
		"laps": "Laps: $[0]",
		"next": "Next",
		"fail": "Fail",
		"success": "Success",
		"inventory": "inventory",
		"map": "map",
		"resume": "resume",
		"audio": "audio",
		"key": "value",
		"mission_title": "Hi, brave looter. I'm Samantha,\nthe grand-shopkeeper-of-all-the-mazes.",
		"mission_invitation": "Here's today's order:",
		"mission_item_desc": "- $[0] $[1].",

		"item_chest": "A CHEST",
		"item_diamond": "A DIAMOND",
		"item_metal": "A piece of METAL",
		"item_potion": "A POTION",
		"item_rock": "A ROCK",
		"item_shield": "A SHIELD",
		"item_sword": "A SWORD",
		"item_wood": "A piece of WOOD",
		"item_skeleton": "A SKELETON",
		"item_phone": "My PHONE",

		"item_ordinary": "that is NORMAL",
		"item_magic": "that is MAGIC",
		"item_cursed": "that is CURSED",
		"item_mypowers": "that opens doors",

		"credits_title": "The legend of the looter and the incredible\nbackpack that never runs out of space",
		"credits_subtitle": "Made in 72 hours for Ludum Dare 42\nTheme: running out of space",
		"credits_design_1": "Designed by:",
		"credits_design_2": "Agar3s and Carenalga",
		"credits_programming_1": "Programming by:",
		"credits_programming_2": "Agar3s and Carenalga (a little)",
		"credits_audio_1": "Audio (music and sfx) by:",
		"credits_audio_2": "Quiet Gecko",
		"credits_art_1": "Art by:",
		"credits_art_2": "Prinfrexita and Carenalga",
		"credits_fonts": "Fonts from: Kenney Game Assets",

		"end_success": "A great-looter is you!!!",
		"end_failure": "You're the shame of looters...",
		"end_tryAgain_success": "Next mission, babeee",
		"end_tryAgain_failure": "Try again",
		"not_ready":"I'm not ready to leave the dungeon",
		"your_mission": "your mission"
	},
	"es": {
		"newgame": "Nuevo Juego",
		"language": "Idioma",
		"back": "regresar",
		"start": "iniciar juego",
		"options": "opciones",
		"credits": "créditos",
		"load": "cargar",
		"delete_data": "eliminar partida guardada",
		"save_data": "guardar",
		"exit": "salir",
		"pause": "pausar",
		"angle": "Angulo: $[0]",
		"laps": "Vueltas: $[0]",
		"next": "Siguiente",
		"fail": "Fracaso",
		"success": "Exito",
		"inventory": "Inventario",
		"map": "Mapa",
		"resume": "continuar",
		"audio": "audio",
		"key": "valor",
		"mission_title": "Hola, valiente saqueador. Soy Lucia,\nla-gran-comerciante-de-todos-los-calabozos.",
		"mission_invitation": "La orden del día es:",
		"mission_item_desc": "- $[0] $[1].",

		"item_chest": "Un COFRE",
		"item_diamond": "Un DIAMANTE",
		"item_metal": "Un trozo de METAL",
		"item_potion": "Una POCIÓN",
		"item_rock": "Un trozo de ROCA",
		"item_shield": "Un ESCUDO",
		"item_sword": "Una ESPADA",
		"item_wood": "Un trozo de MADERA",
		"item_skeleton": "Un ESQUELETO",
		"item_phone": "MI TELEFONO",

		"item_ordinary": "que sea NORMAL",
		"item_magic": "que sea MÁGICO(A)",
		"item_cursed": "que esté MALDITO(A)",
		"item_mypowers": "que abre puertas",

		"credits_title": "The legend of the looter and the incredible\nbackpack that never runs out of space",
		"credits_subtitle": "Hecho en 72 horas para el Ludum Dare 42\nTema: Running out of space",
		"credits_design_1": "Diseño por:",
		"credits_design_2": "Agar3s y Carenalga",
		"credits_programming_1": "Programación por:",
		"credits_programming_2": "Agar3s y Carenalga (un poco)",
		"credits_audio_1": "Audio (música y sfx) por:",
		"credits_audio_2": "Quiet Gecko",
		"credits_art_1": "Arte por:",
		"credits_art_2": "Prinfrexita y Carenalga",
		"credits_fonts": "Fuentes tomadas de: Kenney Game Assets",

		"end_success": "¡¡¡Eres el mejor\nsaqueador!!!",
		"end_failure": "Has fallado como saqueador...",
		"end_tryAgain_success": "Siguiente misión",
		"end_tryAgain_failure": "Volver a intentar",
		"not_ready": "No estoy listo para salir del calabozo",
		"your_mission": "Tu misión"
	}
}